cli_interface/__init__.py
cli_interface/cli.py
cli_interface/message_maker.py
cli_interface/user_interface.py
git_scripts/__init__.py
git_scripts/git_diff_fetcher.py
git_scripts/git_history_analyzer.py
git_scripts/retroactive_commit.py
openai_integration/__init__.py
openai_integration/gpt_client.py
openai_integration/prompt_builder.py
openai_integration/response_processor.py
ComIss-0.1.3.dist-info/LICENSE
ComIss-0.1.3.dist-info/METADATA
ComIss-0.1.3.dist-info/WHEEL
ComIss-0.1.3.dist-info/entry_points.txt
ComIss-0.1.3.dist-info/top_level.txt
ComIss-0.1.3.dist-info/RECORD
