Metadata-Version: 2.1
Name: ComIss
Version: 0.1.3
Summary: Commitment Issues
Home-page: https://github.com/edwardyeung04/commitment-issues
Author: ComIss team
Author-email: boazwu@uw.edu
Classifier: Programming Language :: Python :: 3
Classifier: License :: OSI Approved :: MIT License
Classifier: Operating System :: OS Independent
Requires-Python: >=3.6
License-File: LICENSE
Requires-Dist: openai==0.28
Requires-Dist: python-dotenv
Requires-Dist: pytest
Requires-Dist: pylint
Requires-Dist: rich
Requires-Dist: click
